Mal_Detector/__init__.py
Mal_Detector/__main__.py
Mal_Detector/banner.py
Mal_Detector/cli.py
Mal_Detector/config.py
Mal_Detector/vt_api.py
mal_detector-2.0.0.dist-info/licenses/LICENSE
mal_detector-2.0.0.dist-info/METADATA
mal_detector-2.0.0.dist-info/WHEEL
mal_detector-2.0.0.dist-info/entry_points.txt
mal_detector-2.0.0.dist-info/top_level.txt
mal_detector-2.0.0.dist-info/RECORD
