Metadata-Version: 2.4
Name: Mal-Detector
Version: 2.0.0
Summary: VirusTotal CLI scanner for files and URLs
Author: Bismoy Ghosh
Classifier: Programming Language :: Python :: 3
Classifier: Operating System :: OS Independent
Requires-Python: >=3.7
License-File: LICENSE
Requires-Dist: requests
Requires-Dist: rich
Requires-Dist: jinja2
Dynamic: author
Dynamic: classifier
Dynamic: description
Dynamic: description-content-type
Dynamic: license-file
Dynamic: requires-dist
Dynamic: requires-python
Dynamic: summary
